datagerry.py
datagerry-0.0.1.dist-info/LICENSE
datagerry-0.0.1.dist-info/METADATA
datagerry-0.0.1.dist-info/WHEEL
datagerry-0.0.1.dist-info/top_level.txt
datagerry-0.0.1.dist-info/RECORD
