Metadata-Version: 2.1
Name: datagerry
Version: 0.0.1
Summary: A limited API client for Datagerry CMDB solution
Author: Patrick St-Louis
Classifier: Programming Language :: Python :: 3
Classifier: License :: OSI Approved :: MIT License
Classifier: Operating System :: OS Independent
Requires-Python: >=3.6
License-File: LICENSE
Requires-Dist: requests
